{"title": "\u6bdb\u6cfd\u4e1c\u5173\u4e8e\u8981\u6ce8\u610f\u53cd\u9769\u547d\u590d\u8f9f\u73b0\u8c61\u7684\u6279\u8bed", "date": "1967-2-28", "authors": ["\u6bdb\u6cfd\u4e1c"], "contents": [{"text": "\u5173\u4e8e\u8981\u6ce8\u610f\u53cd\u9769\u547d\u590d\u8f9f\u73b0\u8c61\u7684\u6279\u8bed", "type": "title"}, {"text": ["\u6bdb\u6cfd\u4e1c"], "type": "authors"}, {"text": "\u4ece\u4e0a\u81f3\u4e0b\u5404\u7ea7\u90fd\u6709\u8fd9\u79cd\u53cd\u9769\u547d\u590d\u8f9f\u7684\u73b0\u8c61\uff0c\u503c\u5f97\u6ce8\u610f\u3002", "type": "paragraph"}]}