{"title": "\u6bdb\u6cfd\u4e1c\u5bf9\u4e00\u4e5d\u4e8c\u5e08\u70ae\u5175\u56e2\u90e8\u5206\u540c\u5fd7\u5173\u4e8e\u4e09\u53cd\u6597\u4e89\u7684\u5efa\u8bae\u4fe1\u7684\u6279\u8bed", "date": "1952-2-16", "authors": ["\u6bdb\u6cfd\u4e1c"], "contents": [{"text": "\u6bdb\u6cfd\u4e1c\u5bf9\u4e00\u4e5d\u4e8c\u5e08\u70ae\u5175\u56e2\u90e8\u5206\u540c\u5fd7\u5173\u4e8e\u4e09\u53cd\u6597\u4e89\u7684\u5efa\u8bae\u4fe1\u7684\u6279\u8bed", "type": "title"}, {"text": ["\u6bdb\u6cfd\u4e1c"], "type": "authors"}, {"text": "\u5b89\u5b50\u6587\u540c\u5fd7\uff1a", "type": "appellation"}, {"text": "\u8bf7\u4f60\u62df\u51fa\u4e00\u4e2a\u5bf9\u6b64\u7c7b\u95ee\u9898\u7684\u5904\u7406\u529e\u6cd5\uff0c\u5e76\u5728\u603b\u515a\u59d4\u8ba8\u8bba\u4e00\u6b21\uff0c\u659f\u914c\u59a5\u5f53\uff0c\u7136\u540e\u63d0\u4ea4\u4e2d\u592e\u3002", "type": "paragraph"}, {"text": "\u00a0\u6bdb\u6cfd\u4e1c\u4e8c\u6708\u5341\u516d\u65e5", "type": "paragraph"}, {"text": "\u6b64\u4ef6\u8bf7\u6284\u53d1\u603b\u515a\u59d4\u5404\u59d4\u5458\u9605\u770b\u3002", "type": "paragraph"}]}