{"title": "\u6bdb\u6cfd\u4e1c\u5173\u4e8e\u8981\u65b0\u534e\u793e\u9009\u9001\u4e94\u53cd\u6750\u6599\u7684\u6279\u8bed", "date": "1952-3-30", "authors": ["\u6bdb\u6cfd\u4e1c"], "contents": [{"text": "\u6bdb\u6cfd\u4e1c\u5173\u4e8e\u8981\u65b0\u534e\u793e\u9009\u9001\u4e94\u53cd\u6750\u6599\u7684\u6279\u8bed", "type": "title"}, {"text": ["\u6bdb\u6cfd\u4e1c"], "type": "authors"}, {"text": "\u5c1a\u6606\u540c\u5fd7\uff1a", "type": "appellation"}, {"text": "\u8bf7\u8be2\u65b0\u534e\u793e\u662f\u5426\u5df2\u5c06\u4e94\u53cd\u6750\u6599\u4e2d\u7684\u7cbe\u5f69\u90e8\uff08\u5206\uff09\u53d1\u7ed9\u5404\u5927\u4e2d\u57ce\u5e02\u53c2\u8003\u3002\u4f8b\u5982\u8fd9\u4e00\u671f\u7684\u524d\u4e09\u6761\u6d88\u606f\u5c31\u90fd\u662f\u53ef\u4ee5\u53d1\u7684\u3002", "type": "paragraph"}, {"text": "\u00a0\u6bdb\u6cfd\u4e1c\u4e09\u6708\u5345\u65e5", "type": "paragraph"}]}