{"title": "\u53cd\u9769\u547d\u7f6a\u72af\u4e94\u767e\u540d\u5224\u51b3", "date": "1951-8-7", "authors": [], "contents": [{"text": "\u53cd\u9769\u547d\u7f6a\u72af\u4e94\u767e\u540d\u5224\u51b3", "type": "title"}, {"text": "\u3010\u6caa\u5e02\u65b0\u95fb\u5904\u8baf\u3011\u672c\u5e02\u516c\u5b89\u53f8\u6cd5\u673a\u5173\u7ecf\u5448\u8bf7\u4e3b\u7ba1\u673a\u5173\u6838\u51c6\u540e\uff0c\u65bc\u6628(\u516d)\u65e5\u5c06\u53cd\u9769\u547d\u7f6a\u72af\u4e94\u25cb\u25cb\u540d\u5206\u522b\u5ba3\u544a\u5224\u5904\u4e00\u5e74\u81f3\u5341\u4e94\u5e74\u7684\u6709\u671f\u5f92\u5211\uff0c\u52a0\u4ee5\u5f3a\u5236\u52b3\u52a8\u6539\u9020\u3002\u8fd9\u4e94\u25cb\u25cb\u540d\u53cd\u9769\u547d\u7f6a\u72af\u59d3\u540d\u7c4d\u8d2f\u5982\u4e0b:", "type": "paragraph"}, {"text": "\u5f6d\u7f57\u91d1 \u91d1\u575b \u738b\u5173\u91d1 \u4e0a\u6d77", "type": "paragraph"}, {"text": "\u90d1\u826e\u5c71 \u5d4a\u53bf \u5468\u5609\u56fd \u5f90\u5dde", "type": "paragraph"}, {"text": "\u590f\u4ec1\u672c \u9547\u6d77 \u6768\u4fca\u5c71 \u7ecd\u5174", "type": "paragraph"}, {"text": "\u5f20\u9e4f\u98de \u6d77\u5b81 \u5434\u6d77\u5fe0 \u6e56\u5317", "type": "paragraph"}, {"text": "\u4f55\u4ec1\u53d1 \u4e0a\u6d77 \u5468\u6069\u6ce2 \u957f\u6c99", "type": "paragraph"}, {"text": "\u6881\u5b89\u5fb7 \u65b0\u4f1a \u5b59\u5b5d\u7af9 \u6c5f\u90fd", "type": "paragraph"}, {"text": "\u9648\u89c2\u82cf \u82cf\u5dde \u5468\u4ec1\u8363 \u5b81\u6ce2", "type": "paragraph"}, {"text": "\u6c64\u8c0b\u6b66 \u6b66\u660c \u5f90\u5dfd\u660e \u7389\u5c71", "type": "paragraph"}, {"text": "\u65b9\u58eb\u6210 \u8bf8\u66a8 \u5f20\u56fd\u5e86  \u6c5f\u9634", "type": "paragraph"}, {"text": "\u53f6\u541b\u4e49 \u5b81\u6ce2 \u9676\u5d07\u6f33 \u6c5f\u9675", "type": "paragraph"}, {"text": "\u90d1\u7ef4\u65b0 \u5434\u5174 \u5f6d\u6f88\u4e4b \u6e58\u4e61", "type": "paragraph"}, {"text": "\u7ae0\u96e8\u9a04 \u6c5f\u90fd \u91d1\u7965\u6839 \u5357\u6c47", "type": "paragraph"}, {"text": "\u6768\u91cc\u68ee \u6b66\u8fdb \u6768\u8343\u53d1 \u65e0\u9521", "type": "paragraph"}, {"text": "\u8983\u6da4\u5bf0 \u5b81\u4e61 \u5f90\u5949\u8d75  \u5949\u5316", "type": "paragraph"}, {"text": "\u738b\u9e3f\u79a7 \u9ad8\u90ae \u7f57\u8302\u7965 \u4e0a\u6d77", "type": "paragraph"}, {"text": "\u6731\u56fd\u7405 \u76d1\u5229 \u5468\u9521\u88d5 \u9547\u6d77", "type": "paragraph"}, {"text": "\u90b5\u5c65\u5747 \u8392\u53bf \u6c88\u4e09\u5ea6  \u6c5f\u9634", "type": "paragraph"}, {"text": "\u5f20\u6811\u6797 \u4e0a\u6d77 \u738b\u5b9d\u94f6 \u4e1c\u53f0", "type": "paragraph"}, {"text": "\u8f9b\u8000\u5ead \u6b66\u57ce \u6731\u6842\u8363 \u5357\u6c47", "type": "paragraph"}, {"text": "\u590f\u53cb\u660e \u76d0\u57ce \u9648\u5e86\u4e91 \u7ecd\u5174", "type": "paragraph"}, {"text": "\u6f58\u5fb7\u660c \u961c\u5b81 \u738b\u987a\u6625 \u5e38\u719f", "type": "paragraph"}, {"text": "\u7ae5\u91d1\u751f \u5b81\u6ce2 \u91d1\u56fd\u826f \u626c\u4e2d", "type": "paragraph"}, {"text": "\u848b\u963f\u56db \u626c\u5dde \u5355\u884c\u4e2d \u65e0\u9521", "type": "paragraph"}, {"text": "\u9646\u60e0\u5fe0 \u4e0a\u6d77 \u5f20\u6bbf\u5085 \u901a\u8fbd", "type": "paragraph"}, {"text": "\u94b1\u6d77\u6797 \u4e0a\u6d77 \u5218\u4e95\u7136 \u6c76\u4e0a", "type": "paragraph"}, {"text": "\u82cf\u4f2f\u8363 \u65e0\u9521 \u5468\u5b50\u95f0 \u5b81\u6ce2", "type": "paragraph"}, {"text": "\u9c8d\u9521\u708e \u65e0\u9521 \u9648\u68a6\u5f71 \u76d0\u57ce", "type": "paragraph"}, {"text": "\u738b\u5927\u5eb7 \u5b81\u6ce2 \u5468\u5b81\u752b \u9547\u6d77", "type": "paragraph"}, {"text": "\u738b\u653f\u5143 \u65e0\u9521 \u674e\u5f69\u7136 \u76d0\u57ce", "type": "paragraph"}, {"text": "\u5468\u9521\u624d \u65e0\u9521 \u6731\u9716   \u5d07\u5fb7", "type": "paragraph"}, {"text": "\u738b\u5176\u6cc9 \u6dee\u9634 \u9648\u5146\u5e86 \u961c\u5b81", "type": "paragraph"}, {"text": "\u535c\u5bfc\u5b98 \u6cf0\u5174 \u4f55\u4ee5\u6210 \u5434\u53bf", "type": "paragraph"}, {"text": "\u5b59\u4ee5\u589e \u5609\u5584 \u8427\u5982\u677e \u6dee\u5b89", "type": "paragraph"}, {"text": "\u9ec4\u9e3f\u624d \u4e0a\u6d77 \u51af\u8000\u594e \u65e0\u9521", "type": "paragraph"}, {"text": "\u94b1\u6839\u5f1f \u5b81\u6ce2 \u5218\u798f\u6839 \u9547\u6c5f", "type": "paragraph"}, {"text": "\u80e1\u9f99\u751f \u5434\u53bf \u5434\u5fd7\u81e3 \u5408\u80a5", "type": "paragraph"}, {"text": "\u9648\u5c27\u521a \u4f59\u59da \u5f20\u5999\u6cc9 \u4e0a\u6d77", "type": "paragraph"}, {"text": "\u738b\u94f6\u751f \u5b81\u6ce2 \u5f90\u4fe1\u6807 \u9547\u6d77", "type": "paragraph"}, {"text": "\u91d1\u594b\u5149 \u4e0a\u6d77 \u987e\u8fde\u5b9d \u65e0\u9521", "type": "paragraph"}, {"text": "\u5362\u957f\u677e \u961c\u5b81 \u5468\u987a\u6c49 \u5609\u5174", "type": "paragraph"}, {"text": "\u5f20\u60e0\u4ead \u6d77\u95e8 \u859b\u6d77\u6839 \u6c5f\u9634", "type": "paragraph"}, {"text": "\u848b\u56fd\u7fa4 \u5b81\u6ce2 \u6768\u5c11\u697c \u76d0\u57ce", "type": "paragraph"}, {"text": "\u6bb7\u6625\u8363 \u65e0\u9521 \u623f\u4fca\u4e49 \u6c49\u53e3", "type": "paragraph"}, {"text": "\u4e01\u5170\u4ead \u8d63\u6986 \u5b59\u94c1\u752b \u6cf0\u5174", "type": "paragraph"}, {"text": "\u9648\u5f00\u5148 \u4e0a\u6d77 \u5c60\u6052\u4fca \u5b81\u6ce2", "type": "paragraph"}, {"text": "\u8427\u9521\u52bb \u5927\u57d4 \u738b\u632f\u65b0 \u6b66\u8fdb", "type": "paragraph"}, {"text": "\u8c22\u5251\u5fe0 \u6885\u53bf \u5218\u6e2d\u80fd \u5927\u57d4", "type": "paragraph"}, {"text": "\u9648\u660c\u5e74 \u6148\u8c3f \u9648\u660e\u6e05 \u5949\u5316", "type": "paragraph"}, {"text": "\u4fde\u56fd\u5e74 \u5b9a\u6d77 \u5434\u6c5f \u56db\u4f1a", "type": "paragraph"}, {"text": "\u51cc\u5bb5\u6b59 \u53bf\u4fde \u9f99\u5e86 \u626c\u5dde", "type": "paragraph"}, {"text": "\u738b\u6d77\u6cc9 \u6cf0\u5dde \u6c88\u4e91 \u4e1c\u53f0", "type": "paragraph"}, {"text": "\u5434\u594e\u6cc9 \u5357\u901a \u5f20\u5c11\u9e4f \u626c\u5dde", "type": "paragraph"}, {"text": "\u738b\u5fc3\u5ef6 \u6cd7\u6d2a \u502a\u5e86\u6210 \u5357\u6c47", "type": "paragraph"}, {"text": "\u7b26\u4e91\u5c71 \u76d0\u57ce \u9648\u4f1f\u6c11 \u4e0a\u6d77", "type": "paragraph"}, {"text": "\u7a0b\u690d\u543e \u961c\u5b81 \u674e\u6587\u8912 \u5609\u5174", "type": "paragraph"}, {"text": "\u65bd\u4ec1\u653f \u4e49\u4e4c \u9648\u666f\u6811 \u5e38\u5dde", "type": "paragraph"}, {"text": "\u5f20\u5ea0\u5143 \u5609\u5b9a \u738b\u56fd\u534e \u9547\u6c5f", "type": "paragraph"}, {"text": "\u738b\u5b9d\u53d1 \u9547\u6c5f \u4e01\u7389\u5764 \u626c\u5dde", "type": "paragraph"}, {"text": "\u6f58\u4e1c\u5982 \u4e0a\u6d77 \u5434\u6b27\u9633 \u4e0a\u6d77", "type": "paragraph"}, {"text": "\u5362\u8f89 \u4e0a\u6d77 \u5f20\u6da6\u9ad8 \u4e0a\u6d77", "type": "paragraph"}, {"text": "\u66f9\u610f\u767d \u961c\u5b81 \u9ec4\u4fdd\u751f \u5ddd\u6c99", "type": "paragraph"}, {"text": "\u5434\u6770\u4eba \u626c\u4e2d \u738b\u6d2a\u5174 \u4e0a\u6d77", "type": "paragraph"}, {"text": "\u94b1\u5fd7\u5143 \u6d77\u5b81 \u9648\u4e91\u7965 \u76d0\u57ce", "type": "paragraph"}, {"text": "\u9a6c\u5b9c\u7532 \u4e0a\u6d77 \u8881\u91d1\u6807 \u5bbf\u8fc1", "type": "paragraph"}, {"text": "\u4e25\u6797\u5b9d \u4e0a\u6d77 \u53f6\u5143\u7965 \u6148\u8c3f", "type": "paragraph"}, {"text": "\u9648\u5b50\u519b \u4e0a\u865e \u5f20\u5b66\u5fe0 \u6d77\u5dde", "type": "paragraph"}, {"text": "\u6c34\u542f\u5149 \u5b81\u6ce2 \u66f9\u56fd\u8bda \u4e0a\u6d77", "type": "paragraph"}, {"text": "\u5f20\u51e4\u82f1 \u65e0\u9521 \u59dc\u6c38\u7ae0 \u5b81\u6ce2", "type": "paragraph"}, {"text": "\u5b59\u4fca\u6625 \u6c5f\u9634 \u5546\u5bb6\u53d1 \u5efa\u9633", "type": "paragraph"}, {"text": "\u8d3e\u52b1\u82f1 \u5929\u6d25 \u5b59\u542f\u660e \u6c5f\u9634", "type": "paragraph"}, {"text": "\u9648\u6587\u9f99 \u5949\u5316 \u5f20\u4e16\u8363 \u4e0a\u6d77", "type": "paragraph"}, {"text": "\u80e1\u5b97\u85e9 \u4e0a\u6d77 \u738b\u6587\u5b9d \u6cf0\u5dde", "type": "paragraph"}, {"text": "\u65b9\u4eae \u8bf8\u66a8 \u674e\u752b \u82cf\u5dde", "type": "paragraph"}, {"text": "\u987e\u6c38\u5eb7 \u6d77\u95e8 \u5510\u4e07\u4f59 \u9ad8\u90ae", "type": "paragraph"}, {"text": "\u94b1\u94e0 \u5b9a\u6d77 \u5510\u8d53\u5584 \u4e0a\u6d77", "type": "paragraph"}, {"text": "\u5f20\u56fd\u57fa \u4e0a\u6d77 \u6731\u8363\u751f \u65e0\u9521", "type": "paragraph"}, {"text": "\u5218\u7956\u57f9 \u6b66\u8fdb \u5218\u56fd\u592b \u9756\u6c5f", "type": "paragraph"}, {"text": "\u5510\u6d77\u6839 \u4e0a\u6d77 \u987e\u9451\u6e56 \u7ecd\u5174", "type": "paragraph"}, {"text": "\u697c\u4ef2\u6bc5 \u5949\u5316 \u80e1\u4f2f\u5eb7 \u4f59\u59da", "type": "paragraph"}, {"text": "\u4e07\u5bcc", "type": "paragraph"}, {"text": "\u6768\u5927\u536b \u5b81\u6ce2 \u5b8b\u69b4\u6839 \u4e0a\u6d77", "type": "paragraph"}, {"text": "\u4faf\u5fe0\u6797 \u5b81\u6ce2 \u4e25\u4f9d\u5e06 \u6ed5\u53bf", "type": "paragraph"}, {"text": "\u6a0a\u826f\u60e0 \u5b81\u6ce2 \u8c37\u695a\u68e0 \u4e0a\u865e", "type": "paragraph"}, {"text": "\u738b\u6842\u99a8 \u4e0a\u6d77 \u5f20\u5bb6\u751f \u7ecd\u5174", "type": "paragraph"}, {"text": "\u676d\u6b63\u6625 \u6c5f\u90fd \u5f20\u5fb7\u9f99 \u82cf\u5dde", "type": "paragraph"}, {"text": "\u5f20\u4e00\u5fc3 \u65e0\u9521 \u9648\u5fb7\u5b9d \u4e0a\u6d77", "type": "paragraph"}, {"text": "\u6f58\u7965\u5b9d \u4e0a\u6d77 \u5b59\u5b9d\u781a \u901a\u53bf", "type": "paragraph"}, {"text": "\u6768\u4f2f\u96c4 \u4e2d\u5c71 \u66f9\u745e\u7965 \u6cf0\u5174", "type": "paragraph"}, {"text": "\u4f55\u5b97\u4f59 \u76d0\u57ce \u9676\u76db\u797a \u5174\u5316", "type": "paragraph"}, {"text": "\u5e94\u826f\u519b \u5b9a\u6d77 \u738b\u53cb\u701b \u5174\u5316", "type": "paragraph"}, {"text": "\u5f90\u5fb7\u8000 \u5434\u5174 \u5b8b\u5b50\u94ed \u4f11\u5b81", "type": "paragraph"}, {"text": "\u738b\u5fb7\u4ec1 \u626c\u5dde \u9ec4\u826f\u5146 \u84dd\u5c71", "type": "paragraph"}, {"text": "\u8c22\u5e73\u51e1 \u4f59\u59da \u5434\u6db5\u6e05 \u5e38\u5dde", "type": "paragraph"}, {"text": "\u5f20\u4e16\u7eaa \u6d66\u6c5f \u9648\u91d1\u6cc9 \u4e0a\u6d77", "type": "paragraph"}, {"text": "\u6768\u6388\u4e4b \u626c\u5dde \u8463\u4e49\u6b66 \u90b9\u53bf", "type": "paragraph"}, {"text": "\u9ad8\u5b50\u6587 \u6c5f\u90fd \u51af\u4e4b\u5149 \u5bcc\u9633", "type": "paragraph"}, {"text": "\u4f59\u5e08\u9f99 \u4e0a\u6d77 \u9646\u8c61\u4e91 \u5609\u5b9a", "type": "paragraph"}, {"text": "\u675c\u65e6\u5e73 \u5b9d\u5c71 \u9ec4\u8d24 \u5b9d\u5c71", "type": "paragraph"}, {"text": "\u91d1\u4ef2\u6cd5 \u4e0a\u6d77 \u4e25\u6c38\u521a \u6cf0\u5174", "type": "paragraph"}, {"text": "\u738b\u5146\u9e92 \u76d0\u57ce \u5f90\u81ea\u9f50 \u8d39\u53bf", "type": "paragraph"}, {"text": "\u59da\u9e9f\u8363 \u6148\u8c3f \u4e07\u5fd7\u5c27 \u5174\u5316", "type": "paragraph"}, {"text": "\u4e25\u5f71 \u4e0a\u6d77 \u675c\u91d1\u6d9b \u4e0a\u6d77", "type": "paragraph"}, {"text": "\u7a0b\u8363\u752b \u5434\u53bf \u9648\u9f99\u5b9d \u4e0a\u6d77", "type": "paragraph"}, {"text": "\u848b\u695a\u8363 \u6c5f\u9634 \u9102\u5fd7\u8fbe \u9547\u6c5f", "type": "paragraph"}, {"text": "\u5f20\u4f2f\u5eb7 \u676d\u5dde \u738b\u7fbd\u7fd4 \u5e38\u5dde", "type": "paragraph"}, {"text": "\u4e50\u7985\u4fe1 \u9633\u6c5f \u5409\u6797 \u4e0a\u6d77", "type": "paragraph"}, {"text": "\u9f9a\u6b63 \u65e0\u9521 \u9648\u4e2d\u82f1 \u5e7f\u6d4e", "type": "paragraph"}, {"text": "\u9093\u9f0e\u60e0 \u65e0\u9521 \u738b\u5fe0\u826f \u957f\u6c99", "type": "paragraph"}, {"text": "\u6768\u6b46 \u6ea7\u9633 \u5434\u9526\u5c27 \u5b81\u6ce2", "type": "paragraph"}, {"text": "\u77f3\u4f01\u836a \u90b5\u9633 \u5f20\u5e0c\u826f \u5408\u5ddd", "type": "paragraph"}, {"text": "\u738b\u91d1\u5fb7 \u961c\u5b81 \u738b\u5ef6\u6587 \u961c\u5b81", "type": "paragraph"}, {"text": "\u5f20\u8fde\u6839 \u8c61\u5c71 \u970d\u672c\u94a7 \u9547\u6c5f", "type": "paragraph"}, {"text": "\u5f20\u677e\u6797 \u76d0\u57ce \u51af\u7ef4\u8c6a \u676d\u5dde", "type": "paragraph"}, {"text": "\u5468\u5e7f\u798f \u626c\u5dde \u8fc7\u987a\u745b \u5b81\u6ce2", "type": "paragraph"}, {"text": "\u66f9\u5baa\u6c11 \u957f\u6c99 \u6731\u9896\u74a0 \u5609\u5b9a", "type": "paragraph"}, {"text": "\u90ed\u7ef4\u5584 \u4e1c\u82d1 \u76db\u963f\u5999 \u5ddd\u6c99", "type": "paragraph"}, {"text": "\u5218\u7389\u748b \u4e0a\u6d77 \u5b63\u6c49\u6797 \u76d1\u57ce", "type": "paragraph"}, {"text": "\u891a\u6e2d\u6cc9 \u65e0\u9521 \u5510\u5c0f\u59b9 \u6b66\u8fdb", "type": "paragraph"}, {"text": "\u987e\u6625\u798f \u65e0\u9521 \u5f90\u4e16\u94a7 \u5b81\u6ce2", "type": "paragraph"}, {"text": "\u8bb8\u5b50\u6797 \u9ec4\u5ca9 \u8bb8\u5efa\u6770 \u4f59\u59da", "type": "paragraph"}, {"text": "\u59da\u6885\u6751 \u4e0a\u6d77 \u8bb8\u5168\u6625 \u4e0a\u6d77", "type": "paragraph"}, {"text": "\u91d1\u5fb7\u4fdd \u4e0a\u6d77 \u9648\u4f9d\u752b \u5b81\u6ce2", "type": "paragraph"}, {"text": "\u4e01\u9882\u5b89 \u677e\u6c5f \u738b\u79c0\u7965 \u5357\u901a", "type": "paragraph"}, {"text": "\u8bb8\u7acb\u592b \u5bff\u53bf \u6d2a\u6c9b\u5e74 \u9547\u6c5f", "type": "paragraph"}, {"text": "\u6731\u7956\u52cb \u5e38\u719f \u5218\u948a \u949f\u7965", "type": "paragraph"}, {"text": "\u8521\u6749\u9f84 \u5b81\u6ce2 \u6731\u8d35\u543e \u6d77\u5b89", "type": "paragraph"}, {"text": "\u7ae0\u7ffc \u957f\u6c99 \u8bb8\u4ecb\u6797 \u65e0\u9521", "type": "paragraph"}, {"text": "\u5f20\u9e3f\u5c71 \u8bf8\u57ce \u5f20\u6839\u9f99 \u4e0a\u6d77", "type": "paragraph"}, {"text": "\u738b\u6cf0", "type": "paragraph"}, {"text": "\u5434\u6811\u6052 \u4e0a\u6d77 \u8bb8\u5609\u5143 \u4e0a\u6d77", "type": "paragraph"}, {"text": "\u6c88\u88d5\u537f \u65e0\u9521 \u6768\u91d1\u8363 \u5927\u57d4", "type": "paragraph"}, {"text": "\u5c39\u671d\u5bcc \u626c\u5dde \u738b\u5b97\u5168 \u76d1\u57ce", "type": "paragraph"}, {"text": "\u5b54\u5fd7\u5174 \u5b81\u6ce2 \u738b\u76f8\u5fd7 \u6c5c\u6c34", "type": "paragraph"}, {"text": "\u738b\u5173\u534e \u5357\u6c47 \u9648\u614e\u752b \u9547\u6d77", "type": "paragraph"}, {"text": "\u9ec4\u798f\u826f \u4e0a\u865e \u65bd\u957f\u6839 \u5357\u901a", "type": "paragraph"}, {"text": "\u5434\u79cb\u6797 \u4e0a\u6d77 \u6731\u627f\u6d69 \u4f59\u59da", "type": "paragraph"}, {"text": "\u5f90\u91d1\u751f \u5b81\u6ce2 \u5f20\u5999\u53d1 \u5357\u901a", "type": "paragraph"}, {"text": "\u590f\u56fd\u6e90 \u626c\u5dde \u5f90\u5353\u537f \u5434\u53bf", "type": "paragraph"}, {"text": "\u6a0a\u667a\u8fdc \u5d07\u660e \u9648\u624b\u6839 \u4e0a\u865e", "type": "paragraph"}, {"text": "\u6731\u5143\u592b \u5e38\u5dde \u987e\u76d8 \u4e0a\u6d77", "type": "paragraph"}, {"text": "\u848b\u5929\u798f \u9547\u6c5f \u738b\u60e0\u6625 \u961c\u5b81", "type": "paragraph"}, {"text": "\u7fc1\u5fb7\u4f51 \u4e50\u6e05 \u76db\u6587\u7965 \u5d07\u660e", "type": "paragraph"}, {"text": "\u88d8\u94f6\u51e4 \u5b81\u6ce2 \u738b\u5fb7\u8d35 \u65e0\u4e3a", "type": "paragraph"}, {"text": "\u5f20\u7167\u6676 \u6c5f\u90fd \u859b\u5efa\u5e73 \u5434\u53bf", "type": "paragraph"}, {"text": "\u8881\u79cb\u781a \u5434\u53bf \u9646\u8363\u534e \u6c5f\u9634", "type": "paragraph"}, {"text": "\u9676\u745e\u6c5f \u51e4\u9633 \u6731\u80b2\u71fd \u5b9d\u5c71", "type": "paragraph"}, {"text": "\u5218\u5176\u9e3e \u5170\u8c3f \u5468\u9521\u5eb7 \u4e0a\u6d77", "type": "paragraph"}, {"text": "\u9648\u6c38\u5eb7 \u957f\u6c99 \u8d75\u58eb\u5143 \u9ec4\u5ca9", "type": "paragraph"}, {"text": "\u9093\u67ac\u67ab \u5357\u4eac \u7ae5\u6708\u534e \u9547\u6c5f", "type": "paragraph"}, {"text": "\u6797\u80dc\u4fdd \u6f6e\u5dde \u90d1\u5b9d\u594e \u5e38\u5dde", "type": "paragraph"}, {"text": "\u5434\u6dd1\u82f1 \u5434\u53bf \u738b\u514b\u4fed \u5bff\u53bf", "type": "paragraph"}, {"text": "\u738b\u5fe0\u4e49 \u51e4\u53f0 \u738b\u4ef2\u826f \u5e38\u5dde", "type": "paragraph"}, {"text": "\u6768\u5b9d \u8d35\u9633\u8c37 \u80e1\u70b3\u5764 \u4e0a\u6d77", "type": "paragraph"}, {"text": "\u738b\u6c49 \u4e0a\u6d77 \u9ec4\u6d77\u9e25 \u5357\u4eac", "type": "paragraph"}, {"text": "\u8d75\u4fca\u81e3 \u626c\u5dde \u80e1\u70b3\u5e74 \u5b81\u6ce2", "type": "paragraph"}, {"text": "\u8d75\u4e91\u9f99 \u5357\u901a \u5510\u542f\u53d1 \u76d1\u57ce", "type": "paragraph"}, {"text": "\u6bd5\u4e91\u9526 \u5170\u8c3f \u738b\u5176\u6587 \u961c\u5b81", "type": "paragraph"}, {"text": "\u5468\u963f\u658c \u6b66\u8fdb \u9648\u70b3\u594e \u7ecd\u5174", "type": "paragraph"}, {"text": "\u5f20\u534e\u752b \u6cf0\u5174 \u5f90\u5929\u67a2 \u911e\u53bf", "type": "paragraph"}, {"text": "\u95fb\u56fd\u5468 \u4e0a\u6d77 \u4e01\u4e00\u9e23 \u4e0a\u6d77", "type": "paragraph"}, {"text": "\u6c88\u8446\u9752 \u592a\u4ed3 \u9646\u8fde\u901a \u5b81\u6ce2", "type": "paragraph"}, {"text": "\u53f2\u658c \u4f59\u59da \u9ec4\u76ca\u5143 \u5ddd\u6c99", "type": "paragraph"}, {"text": "\u5b59\u7965\u6cf0 \u5982\u768b \u595a\u9038 \u91d1\u5c71", "type": "paragraph"}, {"text": "\u9648\u5fd7\u6797 \u4e0a\u6d77 \u5d14\u5e0c\u9035 \u911e\u53bf", "type": "paragraph"}, {"text": "\u7f57\u6c38\u826f \u592a\u4ed3 \u5f20\u65b0\u9ad8 \u5b9a\u6d77", "type": "paragraph"}, {"text": "\u5434\u51ac\u99a5 \u5b81\u6ce2 \u7fdf\u5146\u5b89 \u76d1\u57ce", "type": "paragraph"}, {"text": "\u59da\u4f73\u672c \u8bf8\u66a8 \u5510\u4f2f\u751f \u65e0\u9521", "type": "paragraph"}, {"text": "\u76db\u632f\u4e3a \u4e0a\u6d77 \u5f90\u7ef3\u6b66 \u5357\u660c", "type": "paragraph"}, {"text": "\u5510\u798f\u9445 \u6606\u5c71 \u683e\u5baa\u7ae0 \u4e91\u68a6", "type": "paragraph"}, {"text": "\u9a6c\u6c60\u80dc \u65b0\u4f1a \u5218\u9e23\u98de \u4e0a\u865e", "type": "paragraph"}, {"text": "\u5f20\u9521\u826f \u5ddd\u6c99 \u5ffb\u8d24\u6587 \u5b81\u6ce2", "type": "paragraph"}, {"text": "\u5468\u6e05\u5d07 \u660e\u987e \u7956\u8303 \u5357\u6c47", "type": "paragraph"}, {"text": "\u590f\u5b50\u4e91 \u4e1c\u53f0 \u5f90\u5eb7\u4e09 \u76d1\u57ce", "type": "paragraph"}, {"text": "\u8bf8\u71ee\u5747 \u5609\u5b9a \u9879\u798f \u5b81\u6ce2", "type": "paragraph"}, {"text": "\u4fde\u9e4f\u6b66 \u8fdb\u7530 \u6c11\u7965 \u626c\u5dde", "type": "paragraph"}, {"text": "\u90d1\u745e\u9e9f \u4e2d\u5c71 \u5f90\u9759\u5bcc \u9547\u6d77", "type": "paragraph"}, {"text": "\u5468\u957f\u4f59 \u626c\u5dde \u738b\u5c11\u537f \u5efa\u9633", "type": "paragraph"}, {"text": "\u4ec7\u6c38", "type": "paragraph"}, {"text": "\u5f20\u9521\u6797 \u5357\u7fd4 \u949f\u6839\u540e \u911e\u53bf", "type": "paragraph"}, {"text": "\u5b8b\u7ee7\u6587 \u8d63\u6986 \u5f90\u5b50\u826f \u5b9c\u5174", "type": "paragraph"}, {"text": "\u8303\u6587\u82f1 \u7ecd\u5174 \u66f9\u8fd1\u667a \u5ddd\u6c99", "type": "paragraph"}, {"text": "\u6c88\u70c8\u8bda \u4e0a\u6d77 \u8881\u6770 \u4e0a\u865e", "type": "paragraph"}, {"text": "\u95f5\u5b58\u4ec1 \u5bbf\u8fc1 \u7ba1\u5b50\u660e \u6c5f\u90fd", "type": "paragraph"}, {"text": "\u738b\u8861\u836a \u65e0\u9521 \u80e1\u8fd0\u6e90 \u6148\u8c3f", "type": "paragraph"}, {"text": "\u4f55\u84c9 \u4e2d\u5c71 \u9648\u53cb\u5fb7 \u6c5f\u9634", "type": "paragraph"}, {"text": "\u4f55\u5bc5 \u4e0a\u6d77 \u5f90\u57f9\u5b66 \u5434\u5174", "type": "paragraph"}, {"text": "\u5f90\u6839\u53d1 \u5357\u4eac \u90b9\u541b\u660e \u65e0\u9521", "type": "paragraph"}, {"text": "\u8bb8\u957f\u5b89 \u9ad8\u90ae \u65b9\u6587\u8000 \u5b81\u6ce2", "type": "paragraph"}, {"text": "\u8d75\u5168\u8f89 \u911e\u53bf \u9646\u57f9\u5b9d \u4e0a\u6d77", "type": "paragraph"}, {"text": "\u51af\u590d\u4ec1 \u6606\u5c71 \u90b1\u57f9\u7405 \u5434\u5174", "type": "paragraph"}, {"text": "\u5218\u5929\u751f \u676d\u5dde \u5434\u9e3f\u7ae0 \u4e0a\u6d77", "type": "paragraph"}, {"text": "\u7ba1\u5176\u5bbd \u4e1c\u53f0 \u987e\u6b63\u5ef6 \u961c\u5b81", "type": "paragraph"}, {"text": "\u5f20\u5fd7\u4e49 \u9547\u6d77 \u9648\u9e9f\u7965 \u5b81\u6ce2", "type": "paragraph"}, {"text": "\u4f59\u6587\u793c \u5bbf\u8fc1 \u6731\u677e\u9e9f \u82cf\u5dde", "type": "paragraph"}, {"text": "\u53f6\u632f\u6e05 \u5b81\u6ce2 \u4faf\u7eaa\u9e9f \u4e0a\u6d77", "type": "paragraph"}, {"text": "\u9646\u6587\u594e \u82cf\u5dde \u9646\u9526\u695a \u5609\u5b9a", "type": "paragraph"}, {"text": "\u5f90\u5fb7\u6e05 \u4e0a\u6d77 \u5f20\u6c49\u537f \u626c\u5dde", "type": "paragraph"}, {"text": "\u8306\u8fde\u751f \u76d1\u57ce \u5434\u56fd\u53d1 \u626c\u5dde", "type": "paragraph"}, {"text": "\u9648\u4e9a\u5149 \u7ecd\u5174 \u674e\u4ee5\u6e90 \u76d1\u57ce", "type": "paragraph"}, {"text": "\u6731\u677e\u6797 \u4e1c\u53f0 \u6797\u79cb\u840d \u4e0a\u6d77", "type": "paragraph"}, {"text": "\u6f58\u9f50\u82ac \u5434\u53bf \u795d\u5fd7\u5eb7 \u7ecd\u5174", "type": "paragraph"}, {"text": "\u5f90\u767b\u5cf0 \u6c5f\u9675 \u90b9\u4fca\u8fde \u4e0a\u6d77", "type": "paragraph"}, {"text": "\u5218\u7115\u589e \u6c5f\u90fd \u9648\u672c\u56fa \u9ece\u5ddd", "type": "paragraph"}, {"text": "\u8bb8\u4ef2\u708e \u6850\u57ce \u9648\u5146\u60e0 \u5949\u5929", "type": "paragraph"}, {"text": "\u8521\u6709\u6797 \u5357\u901a \u718a\u5929\u7532 \u957f\u6c99", "type": "paragraph"}, {"text": "\u9648\u6cf0 \u4e0a\u6d77 \u5f20\u6587\u7965 \u4e0a\u6d77", "type": "paragraph"}, {"text": "\u8a79\u745e\u797a \u4e1c\u839e \u5085\u5b50\u7965 \u8d35\u9633", "type": "paragraph"}, {"text": "\u91d1\u8363\u660c \u5b9a\u6d77 \u718a\u5b50\u5b89 \u6cd7\u9633", "type": "paragraph"}, {"text": "\u6731\u7965\u5fbd \u5b9a\u6d77 \u5f90\u57f9\u6587 \u4e0a\u6d77", "type": "paragraph"}, {"text": "\u6768\u67cf\u6d9b \u4f59\u59da \u5f20\u5b50\u53cb \u65b0\u7edb", "type": "paragraph"}, {"text": "\u90ed\u6b63\u9f99 \u626c\u5dde \u7941\u6797\u751f \u76d1\u57ce", "type": "paragraph"}, {"text": "\u9648\u661f\u5143 \u5d07\u660e \u5f90\u6d77\u9716 \u5170\u8c3f", "type": "paragraph"}, {"text": "\u66f9\u4fe1\u7136 \u5b81\u6ce2 \u4f55\u7eaa\u5764 \u6c5f\u9634", "type": "paragraph"}, {"text": "\u53f2\u8d24\u9686 \u5b81\u6ce2 \u5434\u77f3\u9e9f \u82cf\u5dde", "type": "paragraph"}, {"text": "\u94b1\u5b50\u6a35 \u6cf0\u5dde \u4e01\u56fd\u5143 \u626c\u5dde", "type": "paragraph"}, {"text": "\u738b\u9e3f\u6797 \u961c\u5b81 \u8463\u5ddd \u9cb2\u6148\u8c3f", "type": "paragraph"}, {"text": "\u623f\u8000\u946b \u5d4a\u53bf \u5f90\u4e50\u96c5 \u5b9a\u6d77", "type": "paragraph"}, {"text": "\u9648\u5fd7\u4f1f \u82cf\u5dde \u9648\u53d7\u748b \u7ecd\u5174", "type": "paragraph"}, {"text": "\u9a6c\u4eba\u7965 \u677e\u6c5f \u80e1\u94ed\u8d24 \u7ecd\u5174", "type": "paragraph"}, {"text": "\u9ec4\u745e\u8446 \u82cf\u5dde \u5468\u6da6\u6e20 \u592a\u4ed3", "type": "paragraph"}, {"text": "\u8c22\u901d\u6c34 \u4f59\u59da \u5085\u660e\u6839 \u4e0a\u6d77", "type": "paragraph"}, {"text": "\u65bd\u6d4e\u5fe0 \u5e38\u5dde \u90b5\u8d53\u7ec5 \u65e0\u9521", "type": "paragraph"}, {"text": "\u5ed6\u6cfd \u957f\u6c99 \u50a8\u500d\u5927 \u5b9c\u5174", "type": "paragraph"}, {"text": "\u5b59\u4ee5\u7389 \u5bff\u53bf \u6797\u5bb6\u6d9b \u95fd\u4faf", "type": "paragraph"}, {"text": "\u5b59\u6842\u751f \u961c\u5b81 \u6f58\u826f \u6b66\u8fdb", "type": "paragraph"}, {"text": "\u97e6\u540d\u6cb3 \u9547\u6c5f \u5b59\u4e07\u548c \u6c5f\u90fd", "type": "paragraph"}, {"text": "\u949f\u6587", "type": "paragraph"}, {"text": "\u738b\u4e9a", "type": "paragraph"}, {"text": "\u5c39\u5927\u9f99 \u9756\u6c5f \u4efb\u660e\u7ae0 \u6d77\u76d1", "type": "paragraph"}, {"text": "\u845b\u5347\u7965 \u5b81\u6d77 \u91d1\u5e7f\u751f \u5982\u768b", "type": "paragraph"}, {"text": "\u5218\u7af9\u7b90 \u5b89\u5e86 \u8305\u6587\u57f9 \u4e0a\u6d77", "type": "paragraph"}, {"text": "\u738b\u9e4f\u98de \u6dee\u9634 \u6f58\u7acb\u660e \u65b0\u4f1a", "type": "paragraph"}, {"text": "\u4f55\u9526\u53cb \u7ecd\u5174 \u674e\u661f\u8f89 \u4e0a\u6d77", "type": "paragraph"}, {"text": "\u674e\u6211\u94a7 \u5e73\u6c5f \u845b\u5f7c\u5fb7 \u4e0a\u6d77", "type": "paragraph"}, {"text": "\u5468\u5251\u5bd2 \u677e\u6c5f \u5f20\u79c0\u5cf0 \u66f9\u53bf", "type": "paragraph"}, {"text": "\u674e\u5baa \u9e64\u5c71 \u8881\u5170\u6839 \u4e0a\u6d77", "type": "paragraph"}, {"text": "\u4e01\u56fd\u748b \u961c\u5b81 \u9648\u9e64\u559c \u6cf0\u5dde", "type": "paragraph"}, {"text": "\u9ec4\u9526\u6d77 \u6cf0\u5dde \u6c88\u6d69\u5174 \u5e38\u5dde", "type": "paragraph"}, {"text": "\u94b1\u8fde\u751f \u676d\u5dde \u8bb8\u677e \u6c5f\u9634", "type": "paragraph"}, {"text": "\u848b\u9f99\u82b3 \u6c5f\u534e \u5434\u8bda \u5de2\u53bf", "type": "paragraph"}, {"text": "\u590f\u5e7c\u83b2 \u4e0a\u6d77 \u5f20\u56fd\u5f5d \u56fa\u59cb", "type": "paragraph"}, {"text": "\u7a0b\u65b0\u68e0 \u6b59\u53bf \u5f20\u661f\u6d77 \u5b9a\u6d77", "type": "paragraph"}, {"text": "\u5f20\u4eae\u901a \u5b81\u6ce2 \u51af\u76d1\u5e86 \u4e0a\u865e", "type": "paragraph"}, {"text": "\u5f20\u7389\u5d10 \u5609\u5584 \u65bd\u58eb\u73cd \u5d07\u660e", "type": "paragraph"}, {"text": "\u9ec4\u798f\u76f8 \u6d77\u95e8 \u8fb9\u6bd3\u826f \u65e0\u9521", "type": "paragraph"}, {"text": "\u9a6c\u4e16\u6d77 \u4e0a\u6d77 \u987e\u8087\u66fe \u5357\u6c47", "type": "paragraph"}, {"text": "\u5f90\u627f\u707f \u4f59\u59da \u845b\u4e2d\u5360 \u5b81\u6d77", "type": "paragraph"}, {"text": "\u595a\u5fb7\u693f \u6b66\u8fdb \u9646\u91d1\u6839 \u5b9d\u5c71", "type": "paragraph"}, {"text": "\u4e25\u6d77\u751f \u4e0a\u6d77 \u5f20\u4e1a\u9f99 \u6c5f\u5b81", "type": "paragraph"}, {"text": "\u9ad8\u6c11\u80dc \u82cf\u5dde \u9f99\u767b\u4e91 \u6c49\u9633", "type": "paragraph"}, {"text": "\u6765\u6e90\uff1a\u300a\u6587\u6c47\u62a5\u300b1951\u5e748\u67087\u65e5", "type": "paragraph"}]}