{"title": "\u6bdb\u6cfd\u4e1c\u5728\u4e00\u5c01\u53cd\u6620\u67d0\u4e9b\u4e2d\u592e\u673a\u5173\u5e72\u90e8\u7528\u516c\u5bb6\u5c0f\u6c7d\u8f66\u63a5\u9001\u5b50\u5973\u4e0a\u5b66\u7684\u6765\u4fe1\u4e0a\u7684\u6279\u8bed", "date": "1951-12-18", "authors": ["\u6bdb\u6cfd\u4e1c"], "contents": [{"text": "\u6bdb\u6cfd\u4e1c\u5728\u4e00\u5c01\u53cd\u6620\u67d0\u4e9b\u4e2d\u592e\u673a\u5173\u5e72\u90e8\u7528\u516c\u5bb6\u5c0f\u6c7d\u8f66\u63a5\u9001\u5b50\u5973\u4e0a\u5b66\u7684\u6765\u4fe1\u4e0a\u7684\u6279\u8bed", "type": "title"}, {"text": ["\u6bdb\u6cfd\u4e1c"], "type": "authors"}, {"text": "\u5c1a\u6606\u540c\u5fd7\u67e5\u660e\u914c\u529e\u3002\u8fd9\u4e2a\u5efa\u8bae\u503c\u5f97\u6ce8\u610f\u3002", "type": "paragraph"}, {"text": "\u00a0\u6bdb\u6cfd\u4e1c\u5341\u4e8c\u6708\u5341\u516b\u65e5", "type": "paragraph"}]}